ovos_media_plugin_chromecast/__init__.py
ovos_media_plugin_chromecast/audio.py
ovos_media_plugin_chromecast/autoconfigure.py
ovos_media_plugin_chromecast/ccast.py
ovos_media_plugin_chromecast/media.py
ovos_media_plugin_chromecast/version.py
ovos_media_plugin_chromecast-0.1.3.dist-info/licenses/LICENSE
ovos_media_plugin_chromecast-0.1.3.dist-info/METADATA
ovos_media_plugin_chromecast-0.1.3.dist-info/WHEEL
ovos_media_plugin_chromecast-0.1.3.dist-info/entry_points.txt
ovos_media_plugin_chromecast-0.1.3.dist-info/top_level.txt
ovos_media_plugin_chromecast-0.1.3.dist-info/RECORD
