Metadata-Version: 2.4
Name: ovos_media_plugin_chromecast
Version: 0.1.3
Summary: chromecast plugin for ovos
Home-page: https://github.com/OpenVoiceOS/ovos-media-plugin-chromecast
Author: JarbasAi
Author-email: jarbasai@mailfence.com
License: Apache-2.0
Keywords: ovos audio video OCP plugin
License-File: LICENSE
Requires-Dist: ovos-plugin-manager<3.0.0,>=0.0.26
Requires-Dist: pychromecast
Requires-Dist: zeroconf
Dynamic: author
Dynamic: author-email
Dynamic: description
Dynamic: description-content-type
Dynamic: home-page
Dynamic: keywords
Dynamic: license
Dynamic: license-file
Dynamic: requires-dist
Dynamic: summary
